financialwords/__init__.py
financialwords/words.txt
financialwords-0.2.1.dist-info/LICENSE.txt
financialwords-0.2.1.dist-info/METADATA
financialwords-0.2.1.dist-info/WHEEL
financialwords-0.2.1.dist-info/top_level.txt
financialwords-0.2.1.dist-info/zip-safe
financialwords-0.2.1.dist-info/RECORD
